gammarers/aws_cdk_errors/__init__.py
gammarers/aws_cdk_errors/py.typed
gammarers/aws_cdk_errors/_jsii/__init__.py
gammarers/aws_cdk_errors/_jsii/aws-cdk-errors@1.2.51.jsii.tgz
gammarers_aws_cdk_errors-1.2.51.dist-info/LICENSE
gammarers_aws_cdk_errors-1.2.51.dist-info/METADATA
gammarers_aws_cdk_errors-1.2.51.dist-info/WHEEL
gammarers_aws_cdk_errors-1.2.51.dist-info/top_level.txt
gammarers_aws_cdk_errors-1.2.51.dist-info/RECORD
